Metadata-Version: 1.1
Name: kill-all-ssh-sessions
Version: 0.1.0
Summary: This tool kills all the running ssh sessions.
Home-page: https://github.com/amolpol98/python-kill-all-ssh-sessions
Author: Amol Pol
Author-email: amolpol98@gmail.com
License: BSD
Platform: any
Classifier: Development Status :: 4 - Beta
Classifier: Environment :: Console
Classifier: Intended Audience :: Developers
Classifier: License :: OSI Approved :: BSD License
Classifier: Operating System :: POSIX
Classifier: Operating System :: MacOS
Classifier: Operating System :: Unix
Classifier: Operating System :: Microsoft :: Windows
Classifier: Programming Language :: Python
Classifier: Programming Language :: Python :: 2
Classifier: Programming Language :: Python :: 3
Classifier: Topic :: Software Development :: Libraries :: Python Modules
